src/__init__.py
src/lib.py
src/main.py
src/telegram.py
obsidian_telegram_reminders-0.1.0.dist-info/entry_points.txt
obsidian_telegram_reminders-0.1.0.dist-info/WHEEL
obsidian_telegram_reminders-0.1.0.dist-info/METADATA
obsidian_telegram_reminders-0.1.0.dist-info/RECORD
