Metadata-Version: 2.1
Name: obsidian-telegram-reminders
Version: 0.1.0
Summary: 
Author: 'Anton Shuvalov'
Author-email: anton@shuvalov.info
Requires-Python: >=3.9,<4.0
Classifier: Programming Language :: Python :: 3
Classifier: Programming Language :: Python :: 3.10
Classifier: Programming Language :: Python :: 3.9
Requires-Dist: python-dotenv (>=0.19.0,<0.20.0)
Requires-Dist: regex (>=2022.3.15,<2023.0.0)
Requires-Dist: requests (>=2.27.1,<3.0.0)
